nonstationarity.cp311-win_amd64.pyd
nonstationarity-0.0.1.dist-info/LICENSE
nonstationarity-0.0.1.dist-info/METADATA
nonstationarity-0.0.1.dist-info/WHEEL
nonstationarity-0.0.1.dist-info/top_level.txt
nonstationarity-0.0.1.dist-info/RECORD
