Metadata-Version: 2.1
Name: nonstationarity
Version: 0.0.1
Summary: Nonstationarity implements the algorithm of nonstationarity measure of data streams.
Home-page: UNKNOWN
Author: Kan Liu
Author-email: liuk@wipm.ac.cn
License: UNKNOWN
Platform: UNKNOWN
Requires-Python: >=3.6
License-File: LICENSE
Provides-Extra: test
Requires-Dist: pytest (>=6.0) ; extra == 'test'
